ArtCollection.py
ArtCollection-0.0.3.dist-info/METADATA
ArtCollection-0.0.3.dist-info/WHEEL
ArtCollection-0.0.3.dist-info/top_level.txt
ArtCollection-0.0.3.dist-info/RECORD
