Metadata-Version: 2.1
Name: ArtCollection
Version: 0.0.3
Summary: Metropolian MuseumAPI objects which converts in json form and then json to html,xml,csv formats and html to pdf
Home-page: UNKNOWN
Author: Affan
License: UNKNOWN
Keywords: ArtCollection,Metropolian Art Collection,Art Collection API
Platform: UNKNOWN
Classifier: Programming Language :: Python :: 3
Classifier: License :: OSI Approved :: MIT License
Classifier: Operating System :: OS Independent
Requires-Python: >=3.7
Requires-Dist: pandas
Requires-Dist: requests
Requires-Dist: flatten-json
Requires-Dist: pdfkit
Requires-Dist: lxml
